aiotrivia/__init__.py
aiotrivia/client.py
aiotrivia/exceptions.py
aiotrivia/http.py
aiotrivia/question.py
aiotrivia-2.0.1.dist-info/LICENSE
aiotrivia-2.0.1.dist-info/METADATA
aiotrivia-2.0.1.dist-info/WHEEL
aiotrivia-2.0.1.dist-info/top_level.txt
aiotrivia-2.0.1.dist-info/RECORD
