Metadata-Version: 2.1
Name: aiotrivia
Version: 2.0.1
Summary: Asynchronous API Wrapper for the OpenTDB Api. (https://opentdb.com/)
Home-page: https://github.com/niztg/aiotrivia
Author: niztg
License: MIT
Project-URL: Discord Server, https://discord.com/invite/2fxKxJH
Keywords: trivia,api,trivia_api,opentdb
Platform: UNKNOWN
Requires-Python: >=3.5.3
Requires-Dist: aiohttp
